zampie_utils/__init__.py
zampie_utils/async_utils.py
zampie_utils/cmd_utils.py
zampie_utils/decorators.py
zampie_utils/file_utils.py
zampie_utils/html_utils.py
zampie_utils/img_utils.py
zampie_utils/logger.py
zampie_utils/pandas_utils.py
zampie_utils/request_utils.py
zampie_utils/singleton.py
zampie_utils/str_utils.py
zampie_utils/time_utils.py
zampie_utils/utils.py
zampie_utils-0.9.1.dist-info/licenses/LICENSE
zampie_utils-0.9.1.dist-info/METADATA
zampie_utils-0.9.1.dist-info/WHEEL
zampie_utils-0.9.1.dist-info/top_level.txt
zampie_utils-0.9.1.dist-info/RECORD
