Metadata-Version: 2.4
Name: zampie_utils
Version: 0.9.1
Summary: A collection of utility functions
Author-email: zampie <zampielzp@gmail.com>
License-Expression: MIT
Project-URL: Homepage, https://github.com/zampie/zampie_utils
Project-URL: Bug Reports, https://github.com/zampie/zampie_utils/issues
Project-URL: Source, https://github.com/zampie/zampie_utils
Keywords: utils,tools,utilities
Classifier: Development Status :: 3 - Alpha
Classifier: Intended Audience :: Developers
Classifier: Programming Language :: Python :: 3
Classifier: Topic :: Software Development :: Libraries :: Python Modules
Requires-Python: >=3.6
License-File: LICENSE
Requires-Dist: pandas
Requires-Dist: chardet
Requires-Dist: rich
Requires-Dist: natsort
Requires-Dist: json5
Requires-Dist: tqdm
Requires-Dist: requests
Dynamic: license-file
